<BODY KONKID="993" KONKNAME="Московская обл, г Подольск, ул Ленинградская, д 7" FILEDATE="2020-06-11 09:30:27" DCID="1">
	<ITEM medid="2470" medprice="160.0"/>
	<ITEM medid="44799" medprice="372.0"/>
	<ITEM medid="42760" medprice="1140.0"/>
	<ITEM medid="9780" medprice="292.0"/>
	<ITEM medid="40383" medprice="301.0"/>
	<ITEM medid="11259" medprice="388.0"/>
	<ITEM medid="15788" medprice="446.0"/>
	<ITEM medid="44510" medprice="511.0"/>
	<ITEM medid="44798" medprice="514.0"/>
	<ITEM medid="27844" medprice="617.0"/>
	<ITEM medid="37017" medprice="1050.0"/>
	<ITEM medid="5302" medprice="23.0"/>
	<ITEM medid="19376" medprice="19.0"/>
	<ITEM medid="37484" medprice="19.0"/>
	<ITEM medid="3449" medprice="54.0"/>
	<ITEM medid="12642" medprice="54.0"/>
	<ITEM medid="5219" medprice="72.0"/>
	<ITEM medid="14584" medprice="122.5"/>
	<ITEM medid="17682" medprice="91.0"/>
	<ITEM medid="12527" medprice="116.0"/>
	<ITEM medid="9701" medprice="114.0"/>
	<ITEM medid="11281" medprice="132.0"/>
	<ITEM medid="428" medprice="134.0"/>
	<ITEM medid="931" medprice="150.0"/>
	<ITEM medid="532" medprice="222.0"/>
	<ITEM medid="8080" medprice="284.0"/>
	<ITEM medid="9569" medprice="250.0"/>
	<ITEM medid="39911" medprice="368.0"/>
	<ITEM medid="43192" medprice="608.0"/>
	<ITEM medid="14430" medprice="1170.0"/>
	<ITEM medid="9610" medprice="1620.0"/>
	<ITEM medid="2152" medprice="45.0"/>
	<ITEM medid="2148" medprice="42.0"/>
	<ITEM medid="2150" medprice="42.0"/>
	<ITEM medid="2149" medprice="42.0"/>
	<ITEM medid="2151" medprice="41.0"/>
	<ITEM medid="9760" medprice="62.0"/>
	<ITEM medid="7738" medprice="63.0"/>
	<ITEM medid="2153" medprice="57.0"/>
	<ITEM medid="2077" medprice="59.0"/>
	<ITEM medid="15591" medprice="68.0"/>
	<ITEM medid="12966" medprice="531.0"/>
	<ITEM medid="9925" medprice="289.0"/>
	<ITEM medid="26269" medprice="310.0"/>
	<ITEM medid="24421" medprice="223.0"/>
	<ITEM medid="4807" medprice="281.0"/>
	<ITEM medid="15572" medprice="599.0"/>
	<ITEM medid="4805" medprice="1010.0"/>
	<ITEM medid="23667" medprice="170.0"/>
	<ITEM medid="29704" medprice="102.0"/>
	<ITEM medid="11014" medprice="99.0"/>
	<ITEM medid="21603" medprice="106.0"/>
	<ITEM medid="17468" medprice="141.0"/>
	<ITEM medid="28332" medprice="165.0"/>
	<ITEM medid="25177" medprice="112.0"/>
	<ITEM medid="26255" medprice="134.0"/>
	<ITEM medid="12540" medprice="151.0"/>
	<ITEM medid="21156" medprice="167.0"/>
	<ITEM medid="9317" medprice="149.0"/>
	<ITEM medid="29738" medprice="144.0"/>
	<ITEM medid="20871" medprice="184.0"/>
	<ITEM medid="29982" medprice="180.0"/>
	<ITEM medid="20870" medprice="187.0"/>
	<ITEM medid="11209" medprice="236.0"/>
	<ITEM medid="28131" medprice="218.0"/>
	<ITEM medid="28337" medprice="230.0"/>
	<ITEM medid="28111" medprice="246.0"/>
	<ITEM medid="46605" medprice="277.0"/>
	<ITEM medid="24751" medprice="168.0"/>
	<ITEM medid="8096" medprice="201.0"/>
	<ITEM medid="8015" medprice="244.0"/>
	<ITEM medid="24718" medprice="272.0"/>
	<ITEM medid="24750" medprice="618.0"/>
	<ITEM medid="30490" medprice="726.0"/>
	<ITEM medid="26147" medprice="869.0"/>
	<ITEM medid="37719" medprice="848.0"/>
	<ITEM medid="24717" medprice="1010.0"/>
	<ITEM medid="36642" medprice="2370.0"/>
	<ITEM medid="9691" medprice="57.0"/>
	<ITEM medid="46337" medprice="68.0"/>
	<ITEM medid="12398" medprice="57.0"/>
	<ITEM medid="41213" medprice="244.1"/>
	<ITEM medid="35090" medprice="84.0"/>
	<ITEM medid="44058" medprice="237.0"/>
	<ITEM medid="43776" medprice="84.0"/>
	<ITEM medid="1117" medprice="53.0"/>
	<ITEM medid="37072" medprice="80.0"/>
	<ITEM medid="2458" medprice="318.0"/>
	<ITEM medid="2813" medprice="221.0"/>
	<ITEM medid="2456" medprice="302.0"/>
	<ITEM medid="26205" medprice="333.0"/>
	<ITEM medid="35989" medprice="245.0"/>
	<ITEM medid="29606" medprice="25.0"/>
	<ITEM medid="13741" medprice="59.0"/>
	<ITEM medid="6350" medprice="157.0"/>
	<ITEM medid="2457" medprice="245.0"/>
	<ITEM medid="45037" medprice="35.0"/>
	<ITEM medid="48317" medprice="149.0"/>
	<ITEM medid="12567" medprice="625.0"/>
	<ITEM medid="5446" medprice="130.0"/>
	<ITEM medid="14132" medprice="1175.0"/>
	<ITEM medid="9426" medprice="375.0"/>
	<ITEM medid="35990" medprice="184.0"/>
	<ITEM medid="3560" medprice="42.0"/>
	<ITEM medid="9827" medprice="525.0"/>
	<ITEM medid="12221" medprice="1025.0"/>
	<ITEM medid="7296" medprice="203.0"/>
	<ITEM medid="34584" medprice="332.0"/>
	<ITEM medid="29818" medprice="450.0"/>
	<ITEM medid="565" medprice="61.0"/>
	<ITEM medid="21780" medprice="204.0"/>
	<ITEM medid="5444" medprice="270.0"/>
	<ITEM medid="23140" medprice="36.0"/>
	<ITEM medid="7566" medprice="172.0"/>
	<ITEM medid="9637" medprice="167.0"/>
	<ITEM medid="9331" medprice="236.0"/>
	<ITEM medid="26413" medprice="236.0"/>
	<ITEM medid="5229" medprice="621.0"/>
	<ITEM medid="26415" medprice="565.0"/>
	<ITEM medid="9251" medprice="618.0"/>
	<ITEM medid="6156" medprice="606.0"/>
	<ITEM medid="24733" medprice="795.0"/>
	<ITEM medid="36844" medprice="1230.0"/>
	<ITEM medid="30381" medprice="14.0"/>
	<ITEM medid="12866" medprice="19.0"/>
	<ITEM medid="26592" medprice="43.0"/>
	<ITEM medid="9416" medprice="30.0"/>
	<ITEM medid="40807" medprice="65.0"/>
	<ITEM medid="40808" medprice="64.0"/>
	<ITEM medid="40806" medprice="65.0"/>
	<ITEM medid="5787" medprice="152.0"/>
	<ITEM medid="8587" medprice="141.0"/>
	<ITEM medid="13274" medprice="141.0"/>
	<ITEM medid="45033" medprice="185.0"/>
	<ITEM medid="13275" medprice="205.0"/>
	<ITEM medid="13136" medprice="214.0"/>
	<ITEM medid="25414" medprice="248.0"/>
	<ITEM medid="13778" medprice="257.0"/>
	<ITEM medid="13777" medprice="259.0"/>
	<ITEM medid="37726" medprice="309.0"/>
	<ITEM medid="8669" medprice="445.0"/>
	<ITEM medid="37728" medprice="378.0"/>
	<ITEM medid="37729" medprice="375.0"/>
	<ITEM medid="7970" medprice="526.0"/>
	<ITEM medid="122" medprice="683.0"/>
	<ITEM medid="11320" medprice="821.0"/>
	<ITEM medid="20954" medprice="826.0"/>
	<ITEM medid="3600" medprice="949.0"/>
	<ITEM medid="21071" medprice="596.0"/>
	<ITEM medid="28180" medprice="960.0"/>
	<ITEM medid="21070" medprice="1390.0"/>
	<ITEM medid="17576" medprice="1250.0"/>
	<ITEM medid="6528" medprice="1140.0"/>
	<ITEM medid="22561" medprice="1350.0"/>
	<ITEM medid="10799" medprice="1250.0"/>
	<ITEM medid="852" medprice="1080.0"/>
	<ITEM medid="7891" medprice="585.0"/>
	<ITEM medid="44740" medprice="272.0"/>
	<ITEM medid="24402" medprice="126.0"/>
	<ITEM medid="6490" medprice="385.0"/>
	<ITEM medid="33600" medprice="15.0"/>
	<ITEM medid="10486" medprice="91.0"/>
	<ITEM medid="11208" medprice="99.0"/>
	<ITEM medid="9206" medprice="379.0"/>
	<ITEM medid="31712" medprice="342.0"/>
	<ITEM medid="36032" medprice="565.0"/>
	<ITEM medid="26061" medprice="551.0"/>
	<ITEM medid="12108" medprice="756.0"/>
	<ITEM medid="36543" medprice="1340.0"/>
	<ITEM medid="44301" medprice="393.0"/>
	<ITEM medid="11971" medprice="427.0"/>
	<ITEM medid="30526" medprice="346.0"/>
	<ITEM medid="31711" medprice="292.0"/>
	<ITEM medid="30618" medprice="632.0"/>
	<ITEM medid="34271" medprice="843.0"/>
	<ITEM medid="44302" medprice="849.0"/>
	<ITEM medid="44304" medprice="476.0"/>
	<ITEM medid="11972" medprice="907.0"/>
	<ITEM medid="17729" medprice="866.0"/>
	<ITEM medid="46434" medprice="2650.0"/>
	<ITEM medid="44303" medprice="1160.0"/>
	<ITEM medid="27127" medprice="531.0"/>
	<ITEM medid="47235" medprice="443.0"/>
	<ITEM medid="44981" medprice="3650.0"/>
	<ITEM medid="44982" medprice="4510.0"/>
	<ITEM medid="44983" medprice="5400.0"/>
	<ITEM medid="22451" medprice="115.0"/>
	<ITEM medid="30103" medprice="149.0"/>
	<ITEM medid="25550" medprice="230.0"/>
	<ITEM medid="41268" medprice="166.0"/>
	<ITEM medid="48086" medprice="78.0"/>
	<ITEM medid="25653" medprice="101.0"/>
	<ITEM medid="9519" medprice="173.0"/>
	<ITEM medid="25910" medprice="146.0"/>
	<ITEM medid="11257" medprice="176.0"/>
	<ITEM medid="32046" medprice="233.0"/>
	<ITEM medid="21696" medprice="233.0"/>
	<ITEM medid="43544" medprice="170.0"/>
	<ITEM medid="14724" medprice="213.0"/>
	<ITEM medid="22701" medprice="216.0"/>
	<ITEM medid="14723" medprice="280.0"/>
	<ITEM medid="11203" medprice="266.0"/>
	<ITEM medid="14720" medprice="874.0"/>
	<ITEM medid="1804" medprice="875.0"/>
	<ITEM medid="664" medprice="1030.0"/>
	<ITEM medid="2678" medprice="1020.0"/>
	<ITEM medid="32018" medprice="1030.0"/>
	<ITEM medid="41712" medprice="878.0"/>
	<ITEM medid="32928" medprice="2050.0"/>
	<ITEM medid="9867" medprice="2130.0"/>
	<ITEM medid="47163" medprice="1860.0"/>
	<ITEM medid="43284" medprice="2060.0"/>
	<ITEM medid="14722" medprice="3120.0"/>
	<ITEM medid="43286" medprice="3270.0"/>
	<ITEM medid="43723" medprice="4260.0"/>
	<ITEM medid="43722" medprice="4740.0"/>
	<ITEM medid="37131" medprice="34.2"/>
	<ITEM medid="48061" medprice="71.0"/>
	<ITEM medid="23010" medprice="115.0"/>
	<ITEM medid="48060" medprice="121.0"/>
	<ITEM medid="48056" medprice="135.5"/>
	<ITEM medid="14099" medprice="153.0"/>
	<ITEM medid="8281" medprice="183.5"/>
	<ITEM medid="8299" medprice="200.0"/>
	<ITEM medid="48059" medprice="195.0"/>
	<ITEM medid="40495" medprice="251.0"/>
	<ITEM medid="21066" medprice="270.0"/>
	<ITEM medid="8298" medprice="278.0"/>
	<ITEM medid="8288" medprice="330.5"/>
	<ITEM medid="8287" medprice="610.0"/>
	<ITEM medid="8296" medprice="540.5"/>
	<ITEM medid="2008" medprice="573.0"/>
	<ITEM medid="40494" medprice="978.0"/>
	<ITEM medid="27965" medprice="3260.0"/>
	<ITEM medid="36636" medprice="74.0"/>
	<ITEM medid="1888" medprice="161.0"/>
	<ITEM medid="14784" medprice="143.0"/>
	<ITEM medid="5253" medprice="152.0"/>
	<ITEM medid="12149" medprice="165.0"/>
	<ITEM medid="41305" medprice="169.0"/>
	<ITEM medid="6589" medprice="258.0"/>
	<ITEM medid="6175" medprice="248.0"/>
	<ITEM medid="6327" medprice="218.0"/>
	<ITEM medid="13197" medprice="243.0"/>
	<ITEM medid="29473" medprice="234.0"/>
	<ITEM medid="33914" medprice="148.0"/>
	<ITEM medid="10821" medprice="243.0"/>
	<ITEM medid="13651" medprice="196.0"/>
	<ITEM medid="8707" medprice="212.0"/>
	<ITEM medid="12144" medprice="253.0"/>
	<ITEM medid="12143" medprice="258.0"/>
	<ITEM medid="27996" medprice="245.0"/>
	<ITEM medid="21181" medprice="272.0"/>
	<ITEM medid="10823" medprice="248.0"/>
	<ITEM medid="15144" medprice="1190.0"/>
	<ITEM medid="15140" medprice="991.0"/>
	<ITEM medid="15145" medprice="1190.0"/>
	<ITEM medid="15137" medprice="1460.0"/>
	<ITEM medid="18338" medprice="1190.0"/>
	<ITEM medid="26906" medprice="966.0"/>
	<ITEM medid="15134" medprice="1130.0"/>
	<ITEM medid="15133" medprice="1010.0"/>
	<ITEM medid="15135" medprice="1230.0"/>
	<ITEM medid="15142" medprice="991.0"/>
	<ITEM medid="26907" medprice="1230.0"/>
	<ITEM medid="18343" medprice="1230.0"/>
	<ITEM medid="32638" medprice="1540.0"/>
	<ITEM medid="15128" medprice="1360.0"/>
	<ITEM medid="15129" medprice="1360.0"/>
	<ITEM medid="32643" medprice="1360.0"/>
	<ITEM medid="15127" medprice="1360.0"/>
	<ITEM medid="15126" medprice="1360.0"/>
	<ITEM medid="18364" medprice="2000.0"/>
	<ITEM medid="15046" medprice="2000.0"/>
	<ITEM medid="26910" medprice="1720.0"/>
	<ITEM medid="32640" medprice="1360.0"/>
	<ITEM medid="15050" medprice="1620.0"/>
	<ITEM medid="15152" medprice="1720.0"/>
	<ITEM medid="15146" medprice="1440.0"/>
	<ITEM medid="15149" medprice="1440.0"/>
	<ITEM medid="15148" medprice="1720.0"/>
	<ITEM medid="32639" medprice="1620.0"/>
	<ITEM medid="15049" medprice="1670.0"/>
	<ITEM medid="26911" medprice="1390.0"/>
	<ITEM medid="15151" medprice="1890.0"/>
	<ITEM medid="15048" medprice="1670.0"/>
	<ITEM medid="15045" medprice="2000.0"/>
	<ITEM medid="26909" medprice="1670.0"/>
	<ITEM medid="15153" medprice="1740.0"/>
	<ITEM medid="15157" medprice="2080.0"/>
	<ITEM medid="15155" medprice="2080.0"/>
	<ITEM medid="26913" medprice="1610.0"/>
	<ITEM medid="15154" medprice="1740.0"/>
	<ITEM medid="26912" medprice="2040.0"/>
	<ITEM medid="15158" medprice="1740.0"/>
	<ITEM medid="14927" medprice="2000.0"/>
	<ITEM medid="15156" medprice="2080.0"/>
</BODY>